fpga_device_monitor/Popup.py
fpga_device_monitor/__init__.py
fpga_device_monitor/__main__.py
fpga_device_monitor/res/icons/down.png
fpga_device_monitor/res/icons/down_full.png
fpga_device_monitor/res/icons/up.png
fpga_device_monitor/res/icons/up_full.png
fpga_device_monitor/res/ui/device.ui
fpga_device_monitor/res/ui/label_slider.ui
fpga_device_monitor/res/ui/main.ui
fpga_device_monitor/res/ui/out_dimmer.ui
fpga_device_monitor/res/ui/out_rgb.ui
fpga_device_monitor/res/ui/out_shutter.ui
fpga_device_monitor/res/ui/out_switch.ui
fpga_device_monitor/widgets/__init__.py
fpga_device_monitor/widgets/colorbutton.py
fpga_device_monitor/widgets/device.py
fpga_device_monitor/widgets/device_ctrl.py
fpga_device_monitor/widgets/dimmer_ctrl.py
fpga_device_monitor/widgets/percent_slider.py
fpga_device_monitor/widgets/rgb_ctrl.py
fpga_device_monitor/widgets/shutter_ctrl.py
fpga_device_monitor/widgets/switch_ctrl.py
fpga_device_monitor/windows/__init__.py
fpga_device_monitor/windows/base.py
fpga_device_monitor/windows/main.py
fpga_device_monitor-0.2.6.dist-info/LICENSE
fpga_device_monitor-0.2.6.dist-info/METADATA
fpga_device_monitor-0.2.6.dist-info/WHEEL
fpga_device_monitor-0.2.6.dist-info/top_level.txt
fpga_device_monitor-0.2.6.dist-info/RECORD
